{
    "asset": "spy",
    "horizon_days": 7,
    "feature_names": [
        "lstm_pred",
        "xgb_pred",
        "VIX",
        "GK_Vol_21d",
        "Sentiment",
        "YieldCurve_10Y2Y",
        "DXY",
        "vix_percentile_252d",
        "return_zscore_90d",
        "roll_corr_qqq_90d"
    ],
    "hit_ratio_lstm": 51.445086705202314,
    "hit_ratio_xgb": 61.27167630057804,
    "hit_ratio_direction_head": 61.27167630057804,
    "rmse_magnitude_head": 0.021537789648823195,
    "hit_ratio_combined": 61.27167630057804,
    "rmse_combined": 0.020857173677728234,
    "direction_feature_importance": {
        "lstm_pred": 0.1101892876098465,
        "xgb_pred": 0.09405729132395278,
        "VIX": 0.11460528381783384,
        "GK_Vol_21d": 0.11604662755055602,
        "Sentiment": 0.0,
        "YieldCurve_10Y2Y": 0.17339698740262524,
        "DXY": 0.23668725067973156,
        "vix_percentile_252d": 0.11222839516478919,
        "return_zscore_90d": 0.04278887645066479,
        "roll_corr_qqq_90d": 0.0
    }
}